cli/__init__.py
cli/eventhandlers.py
cli/nuttercli.py
cli/reportsman.py
cli/resultsvalidator.py
common/__init__.py
common/api.py
common/apiclient.py
common/apiclientresults.py
common/authconfig.py
common/httpretrier.py
common/pickleserializable.py
common/resultreports.py
common/resultsview.py
common/scheduler.py
common/statuseventhandler.py
common/stringwriter.py
common/testexecresults.py
common/testresult.py
common/utils.py
runtime/__init__.py
runtime/fixtureloader.py
runtime/nutterfixture.py
runtime/runner.py
runtime/testcase.py
tests/__init__.py
tests/cli/__init__.py
tests/cli/test_eventhandlers.py
tests/cli/test_nuttercli.py
tests/cli/test_reportsman.py
tests/cli/test_resultsvalidator.py
tests/databricks/__init__.py
tests/databricks/test_apiclient.py
tests/databricks/test_authconfig.py
tests/databricks/test_httpretrier.py
tests/databricks/test_utils.py
tests/nutter/__init__.py
tests/nutter/test_api.py
tests/nutter/test_apiclientresults.py
tests/nutter/test_resultreports.py
tests/nutter/test_resultsview.py
tests/nutter/test_scheduler.py
tests/nutter/test_statuseventhandler.py
tests/nutter/test_testexecresults.py
tests/nutter/test_testresult.py
tests/runtime/__init__.py
tests/runtime/test_fixtureloader.py
tests/runtime/test_nutterfixture.py
tests/runtime/test_nutterfixure_fullroundtriptests.py
tests/runtime/test_runner.py
tests/runtime/test_testcase.py
tests/runtime/testnutterfixturebuilder.py
nutter-0.1.35.dist-info/LICENSE
nutter-0.1.35.dist-info/METADATA
nutter-0.1.35.dist-info/WHEEL
nutter-0.1.35.dist-info/entry_points.txt
nutter-0.1.35.dist-info/top_level.txt
nutter-0.1.35.dist-info/RECORD
