Metadata-Version: 2.1
Name: nutter
Version: 0.1.35
Summary: A databricks notebook testing library
Home-page: https://github.com/microsoft/nutter
Author: Jesus Aguilar, Rob Bagby
Author-email: jesus.aguilar@microsoft.com, rob.bagby@microsoft.com
Classifier: Programming Language :: Python :: 3
Classifier: License :: OSI Approved :: MIT License
Classifier: Operating System :: OS Independent
Requires-Python: >=3.7.0
License-File: LICENSE
